TransformerModelDI/TransformerModel.py
TransformerModelDI/__init__.py
TransformerModels-0.3.6.dist-info/METADATA
TransformerModels-0.3.6.dist-info/WHEEL
TransformerModels-0.3.6.dist-info/top_level.txt
TransformerModels-0.3.6.dist-info/RECORD
