Metadata-Version: 2.1
Name: TransformerModels
Version: 0.3.6
Summary: UNKNOWN
Home-page: UNKNOWN
License: UNKNOWN
Download-URL: https://github.com/JoPulido123/TransformerModelDI/archive/refs/tags/0.3.6.tar.gz
Platform: UNKNOWN
Requires-Dist: pandas
Requires-Dist: setfit
